<?xml version="1.0" encoding="UTF-8" standalone="no"?>
<!DOCTYPE tiles-definitions PUBLIC "-//Apache Software Foundation//DTD Tiles Configuration 2.1//EN" "http://tiles.apache.org/dtds/tiles-config_2_1.dtd">
<tiles-definitions>
    <definition extends="default" name="treatmentadvices/list">
        <put-attribute name="body" value="/WEB-INF/views/treatmentadvices/list.jspx"/>
    </definition>
<definition extends="default" name="treatmentadvices/show">
        <put-attribute name="body" value="/WEB-INF/views/treatmentadvices/show.jspx"/>
    </definition>
<definition extends="default" name="treatmentadvices/create">
        <put-attribute name="body" value="/WEB-INF/views/treatmentadvices/create.jspx"/>
    </definition>
<definition extends="default" name="treatmentadvices/update">
        <put-attribute name="body" value="/WEB-INF/views/treatmentadvices/update.jspx"/>
    </definition>
<definition extends="blank" name="treatmentadvices/drugdosages">
        <put-attribute name="body" value="/WEB-INF/views/treatmentadvices/drugdosages.jspx"/>
    </definition>
</tiles-definitions>
